[{"__symbolic":"module","version":4,"metadata":{"EditFormActionTypes":{"EDIT_FORM":"[FORM][EDIT] EDIT_FORM","EDIT_FORM_START":"[FORM][EDIT] EDIT_FORM_START","EDIT_FORM_SUCCEED":"[FORM][EDIT] EDIT_FORM_SUCCEED","EDIT_FORM_FAILED":"[FORM][EDIT] EDIT_FORM_FAILED"},"EditFormAction":{"__symbolic":"class","members":{"__ctor__":[{"__symbolic":"constructor","parameters":[{"__symbolic":"reference","module":"../models","name":"FormSchemaModel","line":13,"character":29}]}]}},"EditFormStartAction":{"__symbolic":"class","members":{"__ctor__":[{"__symbolic":"constructor","parameters":[{"__symbolic":"reference","module":"../models","name":"FormSchemaModel","line":13,"character":29}]}]}},"EditFormSucceedAction":{"__symbolic":"class","members":{"__ctor__":[{"__symbolic":"constructor","parameters":[{"__symbolic":"reference","module":"../models","name":"FormSchemaModel","line":13,"character":29}]}]}},"EditFormFailedAction":{"__symbolic":"class"},"EditFormActions":{"__symbolic":"interface"}}}]